{
    "document": "bfc_script_docs",
    "section": "Geral",
    "subsection": "",
    "subsubsection": "",
    "content": "```bfc-script\nnumeros = [1,2,3]\npercorrer(de:1, ate:3, itens: numeros){\nimprimir item\n}\n// Irá imprimir os números 1, 2 e 3\n```45  \nA tabela EVENTOS representa possíveis eventos do cálculo da folha de pagamento, onde cada evento tem respectivamente um script. Esta tabela é aplicavel para o caso de uso calculo da folha.  \n```bfc-script\nnumeros = [1,2,3]\npercorrer(de:1, ate:3, itens: numeros){\nimprimir item\n}\n// Irá imprimir os números 1, 2 e 3\n```46",
    "metadata": {
        "source": "./bfc_script_docs.md"
    },
    "contains_code": true
}