{
    "document": "bfc_script_docs",
    "section": "Geral",
    "subsection": "",
    "subsubsection": "",
    "content": "```bfc-script\nnumeros = [1,2,3,4]\npercorrer(numeros){\nse(item == 3){\nparar()\n}\nimprimir item\n}\n8.\n//As instruções fora do comando percorrer serão executadas normalmente, somente o comando percorrer\n//será interrompido e não todo o script\nimprimir 'Ok'\n```3  \n##### sobrepor  \nSobrepõe um texto em outro em uma determinada posição e com uma quantidade especifica de caracteres.  \n```bfc-script\nnumeros = [1,2,3,4]\npercorrer(numeros){\nse(item == 3){\nparar()\n}\nimprimir item\n}\n8.\n//As instruções fora do comando percorrer serão executadas normalmente, somente o comando percorrer\n//será interrompido e não todo o script\nimprimir 'Ok'\n```4  \n_Alternativa_  \n```bfc-script\nnumeros = [1,2,3,4]\npercorrer(numeros){\nse(item == 3){\nparar()\n}\nimprimir item\n}\n8.\n//As instruções fora do comando percorrer serão executadas normalmente, somente o comando percorrer\n//será interrompido e não todo o script\nimprimir 'Ok'\n```5  \n##### substituir",
    "metadata": {
        "source": "./bfc_script_docs.md"
    },
    "contains_code": true
}